{
  "titulo": "Curso de Trading Master Gratuito",
  "slogan": "Aprende a interpretar patrones de velas y domina la acción del precio para mejorar tu trading.",
  "video": {
    "src": "https://youtu.be/t7DSQyLa7Ro?si=zj7NjIHDXSwEupdm&t=8",
    "poster": "",
    "alt": "Video de bienvenida"
  },
  "instructor": {
    "nombre": "Pietro Giordano",
    "titulo": "Instructor Senior & Trader",
    "foto": "teacher.webp"
  },
  "concepto": [
    "¡Bienvenido al <em>Trading Master Gratuito</em>! Este curso está diseñado para transformar tu enfoque del trading y llevarte al siguiente nivel. Aprende las estrategias más efectivas, domina el análisis técnico, y toma decisiones de inversión como un profesional. Con nuestro enfoque práctico y accesible, podrás dominar los mercados y obtener resultados consistentes.",
    "En este video promocional, descubrirás todo lo que <em>Trading Master Gratuito</em> tiene para ofrecer:",
    "Técnicas avanzadas de trading",
    "Análisis de mercados en tiempo real",
    "Estrategias de gestión de riesgos",
    "Material exclusivo y actualizado"
  ],
  "paraQuien": [
    "Principiantes absolutos que quieren iniciar desde cero.",
    "Traders intermedios que no logran consistencia.",
    "Personas un estilo de vida distinto."
  ],
  "requisitos": [
    "Internet de alta velocidad",
    "Computadora de escritorio ambientes Windows o Mac",
    "Este Curso de Velas es un excelente complemento para el Curso Master Pro Académico"
  ],
  "destrezas": [
    {
      "icono": "insights",
      "titulo": "Análisis Técnico",
      "descripcion": "Domina chartismo, indicadores y estructura de mercado."
    },
    {
      "icono": "psychology",
      "titulo": "Psicotrading",
      "descripcion": "Controla tus emociones y opera con disciplina férrea."
    },
    {
      "icono": "account_balance",
      "titulo": "Gestión de Capital",
      "descripcion": "Aprende a proteger tu dinero antes de multiplicarlo."
    },
    {
      "icono": "school",
      "titulo": "Educación Financiera",
      "descripcion": "Aprende los fundamentos para tomar mejores decisiones de inversión."
    }
  ],
  "planEstudios": {
    "resumen": {
      "secciones": 1,
      "clases": 5,
      "duracion": "52 min"
    },
    "secciones": [
      {
        "nombre": "Introducción",
        "resumen": {
          "clases": 5,
          "duracion": "53 min"
        },
        "contenido": [
          {"titulo": "Introducción", "tiempo": "42:53"},
          {"titulo": "Zonas de entrada", "tiempo": "01:15"},
          {"titulo": "Divergencias", "tiempo": "02:09"},
          {"titulo": "Fibonacci", "tiempo": "02:57"},
          {"titulo": "Sesiones", "tiempo": "03:18"}
        ]
      }
    ]
  }
}
